miso_client/__init__.py
miso_client/errors.py
miso_client/py.typed
miso_client/api/__init__.py
miso_client/api/auth_api.py
miso_client/api/logs_api.py
miso_client/api/permissions_api.py
miso_client/api/roles_api.py
miso_client/api/types/__init__.py
miso_client/api/types/auth_types.py
miso_client/api/types/logs_types.py
miso_client/api/types/permissions_types.py
miso_client/api/types/roles_types.py
miso_client/models/__init__.py
miso_client/models/config.py
miso_client/models/error_response.py
miso_client/models/filter.py
miso_client/models/filter_schema.py
miso_client/models/pagination.py
miso_client/models/sort.py
miso_client/services/__init__.py
miso_client/services/application_context.py
miso_client/services/auth.py
miso_client/services/cache.py
miso_client/services/encryption.py
miso_client/services/logger.py
miso_client/services/logger_chain.py
miso_client/services/permission.py
miso_client/services/redis.py
miso_client/services/role.py
miso_client/services/unified_logger.py
miso_client/utils/__init__.py
miso_client/utils/audit_log_queue.py
miso_client/utils/auth_cache_helpers.py
miso_client/utils/auth_strategy.py
miso_client/utils/auth_utils.py
miso_client/utils/circuit_breaker.py
miso_client/utils/client_token_manager.py
miso_client/utils/config_loader.py
miso_client/utils/controller_url_resolver.py
miso_client/utils/data_masker.py
miso_client/utils/environment_token.py
miso_client/utils/error_utils.py
miso_client/utils/fastapi_endpoints.py
miso_client/utils/fastapi_logger_middleware.py
miso_client/utils/filter.py
miso_client/utils/filter_applier.py
miso_client/utils/filter_coercion.py
miso_client/utils/filter_parser.py
miso_client/utils/filter_schema.py
miso_client/utils/flask_endpoints.py
miso_client/utils/flask_logger_middleware.py
miso_client/utils/http_client.py
miso_client/utils/http_client_auth_helpers.py
miso_client/utils/http_client_logging.py
miso_client/utils/http_client_logging_helpers.py
miso_client/utils/http_client_query_helpers.py
miso_client-3.9.0.dist-info/licenses/LICENSE
miso_client-3.9.0.dist-info/METADATA
miso_client-3.9.0.dist-info/WHEEL
miso_client-3.9.0.dist-info/top_level.txt
miso_client-3.9.0.dist-info/RECORD
