Metadata-Version: 2.4
Name: miso-client
Version: 3.9.0
Summary: Python client SDK for AI Fabrix authentication, authorization, and logging
Home-page: https://github.com/aifabrix/miso-client-python
Author: AI Fabrix Team
Author-email: AI Fabrix Team <team@aifabrix.ai>
Maintainer-email: AI Fabrix Team <team@aifabrix.ai>
License-Expression: MIT
Project-URL: Homepage, https://github.com/aifabrix/miso-client-python
Project-URL: Documentation, https://docs.aifabrix.ai/miso-client-python
Project-URL: Repository, https://github.com/aifabrix/miso-client-python
Project-URL: Issues, https://github.com/aifabrix/miso-client-python/issues
Keywords: authentication,authorization,rbac,jwt,redis,logging,aifabrix,miso
Classifier: Development Status :: 4 - Beta
Classifier: Intended Audience :: Developers
Classifier: Operating System :: OS Independent
Classifier: Programming Language :: Python :: 3
Classifier: Programming Language :: Python :: 3.8
Classifier: Programming Language :: Python :: 3.9
Classifier: Programming Language :: Python :: 3.10
Classifier: Programming Language :: Python :: 3.11
Classifier: Programming Language :: Python :: 3.12
Classifier: Topic :: Software Development :: Libraries :: Python Modules
Classifier: Topic :: Security
Classifier: Topic :: System :: Logging
Requires-Python: >=3.8
License-File: LICENSE
Requires-Dist: pydantic>=2.0.0
Requires-Dist: httpx>=0.25.0
Requires-Dist: redis[hiredis]>=5.0.0
Requires-Dist: PyJWT>=2.8.0
Requires-Dist: cryptography>=41.0.0
Requires-Dist: python-dotenv>=1.0.0
Provides-Extra: dev
Requires-Dist: pytest>=7.4.3; extra == "dev"
Requires-Dist: pytest-asyncio>=0.21.1; extra == "dev"
Requires-Dist: pytest-mock>=3.12.0; extra == "dev"
Requires-Dist: pytest-cov>=4.1.0; extra == "dev"
Requires-Dist: black>=23.0.0; extra == "dev"
Requires-Dist: isort>=5.12.0; extra == "dev"
Requires-Dist: mypy>=1.5.0; extra == "dev"
Requires-Dist: ruff>=0.1.0; extra == "dev"
Provides-Extra: flask
Requires-Dist: flask>=2.0.0; extra == "flask"
Provides-Extra: fastapi
Requires-Dist: fastapi>=0.100.0; extra == "fastapi"
Dynamic: author
Dynamic: home-page
Dynamic: license-file
Dynamic: requires-python
